Metadata-Version: 1.0
Name: taskpacker
Version: 0.1.1
Summary: UNKNOWN
Home-page: UNKNOWN
Author: Valentin
Author-email: UNKNOWN
License: MIT
Platform: UNKNOWN
